texxd/__init__.py
texxd/app.py
texxd/hex_editor.py
texxd/hex_file.py
texxd/hex_view.py
texxd/log.py
texxd/columns/__init__.py
texxd/columns/address.py
texxd/columns/ascii.py
texxd/columns/column.py
texxd/columns/hex.py
texxd/cursors/__init__.py
texxd/cursors/ascii_cursor.py
texxd/cursors/cursor.py
texxd/cursors/hex_cursor.py
texxd/highlighters/__init__.py
texxd/highlighters/data.py
texxd/highlighters/highlighter.py
texxd/highlighters/highlights.py
texxd-0.0.1.dist-info/entry_points.txt
texxd-0.0.1.dist-info/licenses/LICENSE.md
texxd-0.0.1.dist-info/WHEEL
texxd-0.0.1.dist-info/METADATA
texxd-0.0.1.dist-info/RECORD
