Metadata-Version: 2.4
Name: texxd
Version: 0.0.1
Summary: A hex editor built with Textual
Author-email: Gareth Davidson <gaz@bitplane.net>
Requires-Python: >=3.10
Classifier: License :: Public Domain
Classifier: Operating System :: OS Independent
Classifier: Topic :: Terminals
Classifier: Topic :: Text Editors
Classifier: Topic :: Software Development :: User Interfaces
Classifier: Environment :: Console
License-File: LICENSE.md
Requires-Dist: textual~=3.5
Requires-Dist: pre-commit ; extra == "dev"
Requires-Dist: pytest ; extra == "dev"
Requires-Dist: coverage ; extra == "dev"
Requires-Dist: pytest-cov ; extra == "dev"
Requires-Dist: build ; extra == "dev"
Requires-Dist: twine ; extra == "dev"
Requires-Dist: ruff ; extra == "dev"
Requires-Dist: pytest-asyncio ; extra == "dev"
Requires-Dist: pydoc-markdown ; extra == "dev"
Project-URL: Bug Tracker, https://github.com/bitplane/texxd/issues
Project-URL: Homepage, https://bitplane.net/dev/python/texxd
Project-URL: Source Code, https://github.com/bitplane/texxd
Provides-Extra: dev
